BDSXlsDriver/BDSXlsDriver.py
BDSXlsDriver/__init__.py
BDSXlsDriver-0.0.1.dist-info/LICENSE
BDSXlsDriver-0.0.1.dist-info/METADATA
BDSXlsDriver-0.0.1.dist-info/WHEEL
BDSXlsDriver-0.0.1.dist-info/top_level.txt
BDSXlsDriver-0.0.1.dist-info/RECORD
