Metadata-Version: 2.1
Name: BDSXlsDriver
Version: 0.0.1
Summary: A small example package
Home-page: https://git.batdongsan.com.vn/DuongNT4/MSV_Batdongsan_Automation_Testing
Author: anhdt1.bds
Author-email: anhdt1@batdongsan.com.vn
License: UNKNOWN
Platform: UNKNOWN
Classifier: Programming Language :: Python :: 3
Classifier: License :: OSI Approved :: MIT License
Classifier: Operating System :: OS Independent
Requires-Python: >=3.6
Requires-Dist: xlrd
Requires-Dist: xlwt
Requires-Dist: robot
Requires-Dist: xlutils
Requires-Dist: robotframework-seleniumlibrary
